tselai/__init__.py
tselai/__main__.py
tselai/cli.py
tselai-0.0.0a0.dist-info/LICENSE
tselai-0.0.0a0.dist-info/METADATA
tselai-0.0.0a0.dist-info/WHEEL
tselai-0.0.0a0.dist-info/entry_points.txt
tselai-0.0.0a0.dist-info/top_level.txt
tselai-0.0.0a0.dist-info/RECORD
