Metadata-Version: 2.1
Name: tselai
Version: 0.0.0a0
Summary: LLM support in SQLite
Home-page: https://github.com/Florents-Tselai/tselai
Author: Florents Tselai
License: MIT License
Project-URL: Issues, https://github.com/Florents-Tselai/tselai/issues
Project-URL: CI, https://github.com/Florents-Tselai/tselai/actions
Project-URL: Changelog, https://github.com/Florents-Tselai/tselai/releases
Requires-Python: >=3.7
License-File: LICENSE
Requires-Dist: click
Requires-Dist: llm
Requires-Dist: setuptools
Requires-Dist: pip
Provides-Extra: test
Requires-Dist: pytest ; extra == 'test'
Requires-Dist: pytest-cov ; extra == 'test'
Requires-Dist: black ; extra == 'test'
Requires-Dist: ruff ; extra == 'test'
Requires-Dist: click ; extra == 'test'
